imrc-0.1.0.dist-info/METADATA
imrc-0.1.0.dist-info/WHEEL
imrc-0.1.0.dist-info/license_files/LICENSE
imrc/__init__.py
imrc/__init__.pyi
imrc/py.typed
imrc/imrc.abi3.so
imrc-0.1.0.dist-info/RECORD
