Metadata-Version: 2.1
Name: imrc
Version: 0.1.0
Classifier: Development Status :: 3 - Alpha
Classifier: Operating System :: OS Independent
Classifier: Programming Language :: Rust
Classifier: License :: OSI Approved :: MIT License
Classifier: Programming Language :: Python :: 3.8
Classifier: Programming Language :: Python :: 3.9
Classifier: Programming Language :: Python :: 3.10
Classifier: Programming Language :: Python :: 3.11
Classifier: Programming Language :: Python :: 3
Classifier: Programming Language :: Python :: Implementation :: CPython
Classifier: Programming Language :: Python :: Implementation :: PyPy
License-File: LICENSE
Summary: Python bindings to Rust's persistent data structures (im-rc)
Keywords: data structures,rust,persistent
Author: Julian Berman
Author-email: Julian+im-rc@GrayVines.com
License: MIT
Requires-Python: >=3.8
